gitopenlib/__init__.py
gitopenlib/libs.py
gitopenlib/helpers/__init__.py
gitopenlib/helpers/mongo.py
gitopenlib/helpers/networks.py
gitopenlib/indicators/__init__.py
gitopenlib/indicators/diversity.py
gitopenlib/indicators/entropy_weight_method.py
gitopenlib/indicators/statistics.py
gitopenlib/utils/__init__.py
gitopenlib/utils/ai.py
gitopenlib/utils/basics.py
gitopenlib/utils/clazz.py
gitopenlib/utils/comatrix.py
gitopenlib/utils/crawler.py
gitopenlib/utils/debuger.py
gitopenlib/utils/files.py
gitopenlib/utils/get_ip.py
gitopenlib/utils/k_cluster.py
gitopenlib/utils/nlp.py
gitopenlib/utils/others.py
gitopenlib/utils/parser.py
gitopenlib/utils/plot.py
gitopenlib/utils/sorts.py
gitopenlib/utils/wonders.py
gitopenlib-0.2.29.34.dist-info/licenses/LICENSE
gitopenlib-0.2.29.34.dist-info/METADATA
gitopenlib-0.2.29.34.dist-info/WHEEL
gitopenlib-0.2.29.34.dist-info/top_level.txt
gitopenlib-0.2.29.34.dist-info/RECORD
