Metadata-Version: 2.4
Name: gitopenlib
Version: 0.2.29.34
Summary: A library containing some useful functions. Powered by GitOPEN.
Home-page: https://github.com/opengit/gitopenlib.git
Author: gitopen
Author-email: gitopen@gmail.com
License: MIT
Classifier: License :: OSI Approved :: MIT License
Classifier: Programming Language :: Python
Classifier: Programming Language :: Python :: 3
Classifier: Programming Language :: Python :: 3.6
Classifier: Programming Language :: Python :: Implementation :: CPython
Classifier: Programming Language :: Python :: Implementation :: PyPy
Requires-Python: >=3.6.0
License-File: LICENSE
Requires-Dist: pandas
Requires-Dist: tqdm
Requires-Dist: psutil
Requires-Dist: emoji
Requires-Dist: jieba
Requires-Dist: matplotlib
Requires-Dist: pymongo
Requires-Dist: scipy
Requires-Dist: seaborn
Requires-Dist: fake_useragent
Requires-Dist: requests
Requires-Dist: lxml
Dynamic: author
Dynamic: author-email
Dynamic: classifier
Dynamic: description
Dynamic: description-content-type
Dynamic: home-page
Dynamic: license
Dynamic: license-file
Dynamic: requires-dist
Dynamic: requires-python
Dynamic: summary
